awsassume/__init__.py
awsassume/__main__.py
awsassume/assume_role.py
awsassume/assume_role_cache_executor.py
awsassume/assume_role_executor.py
awsassume/assume_role_executor_factory.py
awsassume/assume_role_no_cache_executor.py
awsassume/command_executor.py
awsassume/command_line_args.py
awsassume/data_models.py
awsassume/environment_variable.py
awsassume/main.py
awsassume/response_cache.py
awsassume/response_cache_adapter.py
awsassume/security_token_service.py
awsassume-0.1.1.dist-info/DESCRIPTION.rst
awsassume-0.1.1.dist-info/METADATA
awsassume-0.1.1.dist-info/RECORD
awsassume-0.1.1.dist-info/WHEEL
awsassume-0.1.1.dist-info/entry_points.txt
awsassume-0.1.1.dist-info/metadata.json
awsassume-0.1.1.dist-info/top_level.txt
