Metadata-Version: 2.0
Name: awsassume
Version: 0.1.1
Summary: Execute AWS CLI commands after assuming role
Home-page: https://github.com/zulhilmizainuddin/aws-assume
Author: Zulhilmi Mohamed Zainuddin
Author-email: zulhilmi.zainuddin@outlook.com
License: MIT
Platform: UNKNOWN
Classifier: Development Status :: 3 - Alpha
Classifier: Intended Audience :: Developers
Classifier: Intended Audience :: System Administrators
Classifier: License :: OSI Approved :: MIT License
Classifier: Programming Language :: Python :: 3 :: Only
Classifier: Programming Language :: Python :: 3.6
Classifier: Environment :: Console
Requires-Python: >=3.6
Requires-Dist: boto3 (>=1.6.16)
Requires-Dist: botocore (>=1.9.16)
Requires-Dist: python-dateutil (<2.7.0,>=2.1)
